BeholderLibrary/__init__.py
robotframework_beholderlibrary-0.1.0.dist-info/LICENSE
robotframework_beholderlibrary-0.1.0.dist-info/METADATA
robotframework_beholderlibrary-0.1.0.dist-info/WHEEL
robotframework_beholderlibrary-0.1.0.dist-info/top_level.txt
robotframework_beholderlibrary-0.1.0.dist-info/RECORD
