Metadata-Version: 2.1
Name: robotframework-beholderlibrary
Version: 0.1.0
Summary: A Robot Framework package to integrate with Beholder, the Zero Defect's Visual Regression Testing platform.
Home-page: https://github.com/zerodefect-testhouse/robotframework-BeholderLibrary
Author: Zero Defect Test House
Author-email: Zero Defect <centro.tecnologia@zero-defect.com.br>
License: Apache License
Project-URL: Homepage, https://github.com/zerodefect-testhouse/robotframework-BeholderLibrary
Project-URL: Bug Tracker, https://github.com/zerodefect-testhouse/robotframework-BeholderLibrary/issues
Keywords: robotframework testing testautomation beholder visualregression selenium webdriver web
Classifier: Programming Language :: Python :: 3
Classifier: Operating System :: OS Independent
Classifier: Topic :: Software Development :: Testing
Classifier: Framework :: Robot Framework
Classifier: Framework :: Robot Framework :: Library
Requires-Python: >=3.7
License-File: LICENSE
Requires-Dist: requests (>=2.27.1)
Requires-Dist: robotframework (>=5.0.1)
Requires-Dist: robotframework-seleniumlibrary (>=6.0.0)
